{
  "slug": "full-time-hunter-i-hunt-the-world",
  "title": "Full-time Hunter: I Hunt the World!",
  "url": "b64:aHR0cHM6Ly9rb21pa2luZG8uY2gva29taWsvZnVsbC10aW1lLWh1bnRlci1pLWh1bnQtdGhlLXdvcmxkLw==",
  "cover_url": "b64:aHR0cHM6Ly9rb21pa2luZG8uY2gvd3AtY29udGVudC91cGxvYWRzLzIwMjYvMDcvRnVsbC10aW1lLUh1bnRlci1JLUh1bnQtdGhlLVdvcmxkLTIzNngzMTMuanBn",
  "type": "Manhua",
  "is_colored": true,
  "rating": 7.0,
  "scraped_at": "2026-07-21T20:28:23.290605",
  "alternative_titles": "全民猎人？我全职猎人!",
  "status": "Berjalan",
  "author": "?",
  "illustrator": "?",
  "genres": [
    "Action",
    "Adventure",
    "Fantasy"
  ],
  "synopsis": "Manhua                    Full-time Hunter: I Hunt the World! yang dibuat oleh komikus bernama\n                    ? ini bercerita tentang\n                    Di dunia di mana binatang mitos berkeliaran dengan bebas, orang hanya bisa menggenggam busur panjang mereka dan mengabdikan diri pada profesi berburu yang mulia. Seorang pemburu senjata memegang senjata yang ditempa dari emas keras, batu, dan esensi dari antek binatang mitos, terikat langsung dengan hidupnya sendiri. Seiring pertumbuhan pemburu, begitu pula senjata aslinya, memberinya kekuatan untuk membunuh makhluk terkuat sekalipun. Seorang pemburu gourmet melakukan perjalanan di seluruh dunia untuk mencari bahan-bahan langka, menarik kekuatan dari makanan yang sangat indah dan menempa tubuh terkuat. Yang terkuat di antara mereka bahkan bisa bertarung dengan binatang mitos dalam pertempuran jarak dekat, bertemu langsung dengan mereka. Seorang pemburu pengetahuan mencari kebijaksanaan melalui buku-buku dan mengungkap sejarah yang terlupakan yang tersembunyi di dalam reruntuhan kuno.",
  "chapters": [
    {
      "chapter": "4",
      "title": "Komik Full-time Hunter: I Hunt the World! Chapter 4",
      "url": "b64:aHR0cHM6Ly9rb21pa2luZG8uY2gvZnVsbC10aW1lLWh1bnRlci1pLWh1bnQtdGhlLXdvcmxkLWNoYXB0ZXItNC8=",
      "date": "2 jam yang lalu"
    },
    {
      "chapter": "3",
      "title": "Komik Full-time Hunter: I Hunt the World! Chapter 3",
      "url": "b64:aHR0cHM6Ly9rb21pa2luZG8uY2gvZnVsbC10aW1lLWh1bnRlci1pLWh1bnQtdGhlLXdvcmxkLWNoYXB0ZXItMy8=",
      "date": "1 minggu yang lalu"
    },
    {
      "chapter": "2",
      "title": "Komik Full-time Hunter: I Hunt the World! Chapter 2",
      "url": "b64:aHR0cHM6Ly9rb21pa2luZG8uY2gvZnVsbC10aW1lLWh1bnRlci1pLWh1bnQtdGhlLXdvcmxkLWNoYXB0ZXItMi8=",
      "date": "2 minggu yang lalu"
    },
    {
      "chapter": "1",
      "title": "Komik Full-time Hunter: I Hunt the World! Chapter 1",
      "url": "b64:aHR0cHM6Ly9rb21pa2luZG8uY2gvZnVsbC10aW1lLWh1bnRlci1pLWh1bnQtdGhlLXdvcmxkLWNoYXB0ZXItMS8=",
      "date": "3 minggu yang lalu"
    }
  ],
  "total_chapters": 4
}