{
  "slug": "age-of-terror",
  "title": "Age of Terror",
  "url": "b64:aHR0cHM6Ly9rb21pa2luZG8uY2gva29taWsvYWdlLW9mLXRlcnJvci8=",
  "cover_url": "b64:aHR0cHM6Ly9rb21pa2luZG8uY2gvd3AtY29udGVudC91cGxvYWRzLzIwMjEvMDkvS29taWstQWdlLW9mLVRlcnJvci0yMzZ4MzEzLmpwZw==",
  "type": "Manhua",
  "is_colored": true,
  "rating": 7.0,
  "scraped_at": "2026-02-10T22:55:04.168169",
  "alternative_titles": "Quanqiu Guiyi Shidai, Global Weird Age, Quánqiú Guǐyì Shídài, Worldwide Strange Era, 全球诡异时代",
  "status": "Berjalan",
  "author": "黑白茶",
  "illustrator": "奇小怪",
  "demographic": "Shounen",
  "themes": [
    "Supernatural"
  ],
  "genres": [
    "Action",
    "Drama",
    "Fantasy",
    "Horror",
    "Psychological"
  ],
  "synopsis": "Manhua                    Age of Terror yang dibuat oleh komikus bernama\n                    黑白茶 ini bercerita tentang\n                    Setelah seratus tahun yang aneh di mana hantu muncul, hanya sepersepuluh umat manusia yang tersisa dan jumlah hantu melebihi jumlah manusia yang tersisa! Untuk bertahan hidup, manusia harus memilih “hantu pendamping” sejak lahir, dan terus-menerus mengolah hantu pendamping mereka sendiri sehingga mereka dapat digunakan untuk melawan hantu lain. Dunia telah memasuki era coeksistensi yang aneh dengan hantu! Dengan bantuan sistem, hantu tak terkalahkan yang dikultivasikan Lin Feng menyebabkan seluruh dunia bergetar",
  "chapters": [
    {
      "chapter": "302",
      "title": "Komik Age of Terror Chapter 302",
      "url": "b64:aHR0cHM6Ly9rb21pa2luZG8uY2gvYWdlLW9mLXRlcnJvci1jaGFwdGVyLTMwMi8=",
      "date": "8 jam yang lalu"
    },
    {
      "chapter": "301",
      "title": "Komik Age of Terror Chapter 301",
      "url": "b64:aHR0cHM6Ly9rb21pa2luZG8uY2gvYWdlLW9mLXRlcnJvci1jaGFwdGVyLTMwMS8=",
      "date": "4 hari yang lalu"
    },
    {
      "chapter": "300",
      "title": "Komik Age of Terror Chapter 300",
      "url": "b64:aHR0cHM6Ly9rb21pa2luZG8uY2gvYWdlLW9mLXRlcnJvci1jaGFwdGVyLTMwMC8=",
      "date": "4 hari yang lalu"
    },
    {
      "chapter": "299",
      "title": "Komik Age of Terror Chapter 299",
      "url": "b64:aHR0cHM6Ly9rb21pa2luZG8uY2gvYWdlLW9mLXRlcnJvci1jaGFwdGVyLTI5OS8=",
      "date": "2 minggu yang lalu"
    },
    {
      "chapter": "298",
      "title": "Komik Age of Terror Chapter 298",
      "url": "b64:aHR0cHM6Ly9rb21pa2luZG8uY2gvYWdlLW9mLXRlcnJvci1jaGFwdGVyLTI5OC8=",
      "date": "2 minggu yang lalu"
    },
    {
      "chapter": "297",
      "title": "Komik Age of Terror Chapter 297",
      "url": "b64:aHR0cHM6Ly9rb21pa2luZG8uY2gvYWdlLW9mLXRlcnJvci1jaGFwdGVyLTI5Ny8=",
      "date": "2 minggu yang lalu"
    },
    {
      "chapter": "296",
      "title": "Komik Age of Terror Chapter 296",
      "url": "b64:aHR0cHM6Ly9rb21pa2luZG8uY2gvYWdlLW9mLXRlcnJvci1jaGFwdGVyLTI5Ni8=",
      "date": "2 minggu yang lalu"
    },
    {
      "chapter": "295",
      "title": "Komik Age of Terror Chapter 295",
      "url": "b64:aHR0cHM6Ly9rb21pa2luZG8uY2gvYWdlLW9mLXRlcnJvci1jaGFwdGVyLTI5NS8=",
      "date": "2 minggu yang lalu"
    },
    {
      "chapter": "294",
      "title": "Komik Age of Terror Chapter  294",
      "url": "b64:aHR0cHM6Ly9rb21pa2luZG8uY2gvYWdlLW9mLXRlcnJvci1jaGFwdGVyLTI5NC8=",
      "date": "3 minggu yang lalu"
    },
    {
      "chapter": "293",
      "title": "Komik Age of Terror Chapter 293",
      "url": "b64:aHR0cHM6Ly9rb21pa2luZG8uY2gvYWdlLW9mLXRlcnJvci1jaGFwdGVyLTI5My8=",
      "date": "3 minggu yang lalu"
    },
    {
      "chapter": "292",
      "title": "Komik Age of Terror Chapter 292",
      "url": "b64:aHR0cHM6Ly9rb21pa2luZG8uY2gvYWdlLW9mLXRlcnJvci1jaGFwdGVyLTI5Mi8=",
      "date": "3 minggu yang lalu"
    },
    {
      "chapter": "291",
      "title": "Komik Age of Terror Chapter 291",
      "url": "b64:aHR0cHM6Ly9rb21pa2luZG8uY2gvYWdlLW9mLXRlcnJvci1jaGFwdGVyLTI5MS8=",
      "date": "4 minggu yang lalu"
    },
    {
      "chapter": "290",
      "title": "Komik Age of Terror Chapter 290",
      "url": "b64:aHR0cHM6Ly9rb21pa2luZG8uY2gvYWdlLW9mLXRlcnJvci1jaGFwdGVyLTI5MC8=",
      "date": "4 minggu yang lalu"
    },
    {
      "chapter": "289",
      "title": "Komik Age of Terror Chapter 289",
      "url": "b64:aHR0cHM6Ly9rb21pa2luZG8uY2gvYWdlLW9mLXRlcnJvci1jaGFwdGVyLTI4OS8=",
      "date": "4 minggu yang lalu"
    },
    {
      "chapter": "288",
      "title": "Komik Age of Terror Chapter 288",
      "url": "b64:aHR0cHM6Ly9rb21pa2luZG8uY2gvYWdlLW9mLXRlcnJvci1jaGFwdGVyLTI4OC8=",
      "date": "4 minggu yang lalu"
    },
    {
      "chapter": "287",
      "title": "Komik Age of Terror Chapter 287",
      "url": "b64:aHR0cHM6Ly9rb21pa2luZG8uY2gvYWdlLW9mLXRlcnJvci1jaGFwdGVyLTI4Ny8=",
      "date": "1 bulan yang lalu"
    },
    {
      "chapter": "286",
      "title": "Komik Age of Terror Chapter 286",
      "url": "b64:aHR0cHM6Ly9rb21pa2luZG8uY2gvYWdlLW9mLXRlcnJvci1jaGFwdGVyLTI4Ni8=",
      "date": "1 bulan yang lalu"
    },
    {
      "chapter": "285",
      "title": "Komik Age of Terror Chapter 285",
      "url": "b64:aHR0cHM6Ly9rb21pa2luZG8uY2gvYWdlLW9mLXRlcnJvci1jaGFwdGVyLTI4NS8=",
      "date": "1 bulan yang lalu"
    },
    {
      "chapter": "284",
      "title": "Komik Age of Terror Chapter 284",
      "url": "b64:aHR0cHM6Ly9rb21pa2luZG8uY2gvYWdlLW9mLXRlcnJvci1jaGFwdGVyLTI4NC8=",
      "date": "1 bulan yang lalu"
    },
    {
      "chapter": "283",
      "title": "Komik Age of Terror Chapter 283",
      "url": "b64:aHR0cHM6Ly9rb21pa2luZG8uY2gvYWdlLW9mLXRlcnJvci1jaGFwdGVyLTI4My8=",
      "date": "2 bulan yang lalu"
    },
    {
      "chapter": "282",
      "title": "Komik Age of Terror Chapter 282",
      "url": "b64:aHR0cHM6Ly9rb21pa2luZG8uY2gvYWdlLW9mLXRlcnJvci1jaGFwdGVyLTI4Mi8=",
      "date": "2 bulan yang lalu"
    },
    {
      "chapter": "281",
      "title": "Komik Age of Terror Chapter 281",
      "url": "b64:aHR0cHM6Ly9rb21pa2luZG8uY2gvYWdlLW9mLXRlcnJvci1jaGFwdGVyLTI4MS8=",
      "date": "2 bulan yang lalu"
    },
    {
      "chapter": "280",
      "title": "Komik Age of Terror Chapter 280",
      "url": "b64:aHR0cHM6Ly9rb21pa2luZG8uY2gvYWdlLW9mLXRlcnJvci1jaGFwdGVyLTI4MC8=",
      "date": "2 bulan yang lalu"
    },
    {
      "chapter": "279",
      "title": "Komik Age of Terror Chapter 279",
      "url": "b64:aHR0cHM6Ly9rb21pa2luZG8uY2gvYWdlLW9mLXRlcnJvci1jaGFwdGVyLTI3OS8=",
      "date": "2 bulan yang lalu"
    },
    {
      "chapter": "278",
      "title": "Komik Age of Terror Chapter 278",
      "url": "b64:aHR0cHM6Ly9rb21pa2luZG8uY2gvYWdlLW9mLXRlcnJvci1jaGFwdGVyLTI3OC8=",
      "date": "2 bulan yang lalu"
    },
    {
      "chapter": "277",
      "title": "Komik Age of Terror Chapter 277",
      "url": "b64:aHR0cHM6Ly9rb21pa2luZG8uY2gvYWdlLW9mLXRlcnJvci1jaGFwdGVyLTI3Ny8=",
      "date": "2 bulan yang lalu"
    },
    {
      "chapter": "276",
      "title": "Komik Age of Terror Chapter 276",
      "url": "b64:aHR0cHM6Ly9rb21pa2luZG8uY2gvYWdlLW9mLXRlcnJvci1jaGFwdGVyLTI3Ni8=",
      "date": "2 bulan yang lalu"
    },
    {
      "chapter": "275",
      "title": "Komik Age of Terror Chapter 275",
      "url": "b64:aHR0cHM6Ly9rb21pa2luZG8uY2gvYWdlLW9mLXRlcnJvci1jaGFwdGVyLTI3NS8=",
      "date": "2 bulan yang lalu"
    },
    {
      "chapter": "274",
      "title": "Komik Age of Terror Chapter 274",
      "url": "b64:aHR0cHM6Ly9rb21pa2luZG8uY2gvYWdlLW9mLXRlcnJvci1jaGFwdGVyLTI3NC8=",
      "date": "2 bulan yang lalu"
    },
    {
      "chapter": "273",
      "title": "Komik Age of Terror Chapter 273",
      "url": "b64:aHR0cHM6Ly9rb21pa2luZG8uY2gvYWdlLW9mLXRlcnJvci1jaGFwdGVyLTI3My8=",
      "date": "2 bulan yang lalu"
    },
    {
      "chapter": "272",
      "title": "Komik Age of Terror Chapter 272",
      "url": "b64:aHR0cHM6Ly9rb21pa2luZG8uY2gvYWdlLW9mLXRlcnJvci1jaGFwdGVyLTI3Mi8=",
      "date": "2 bulan yang lalu"
    },
    {
      "chapter": "271",
      "title": "Komik Age of Terror Chapter 271",
      "url": "b64:aHR0cHM6Ly9rb21pa2luZG8uY2gvYWdlLW9mLXRlcnJvci1jaGFwdGVyLTI3MS8=",
      "date": "2 bulan yang lalu"
    },
    {
      "chapter": "270",
      "title": "Komik Age of Terror Chapter 270",
      "url": "b64:aHR0cHM6Ly9rb21pa2luZG8uY2gvYWdlLW9mLXRlcnJvci1jaGFwdGVyLTI3MC8=",
      "date": "2 bulan yang lalu"
    },
    {
      "chapter": "269",
      "title": "Komik Age of Terror Chapter 269",
      "url": "b64:aHR0cHM6Ly9rb21pa2luZG8uY2gvYWdlLW9mLXRlcnJvci1jaGFwdGVyLTI2OS8=",
      "date": "2 bulan yang lalu"
    },
    {
      "chapter": "268",
      "title": "Komik Age of Terror Chapter 268",
      "url": "b64:aHR0cHM6Ly9rb21pa2luZG8uY2gvYWdlLW9mLXRlcnJvci1jaGFwdGVyLTI2OC8=",
      "date": "2 bulan yang lalu"
    },
    {
      "chapter": "267",
      "title": "Komik Age of Terror Chapter 267",
      "url": "b64:aHR0cHM6Ly9rb21pa2luZG8uY2gvYWdlLW9mLXRlcnJvci1jaGFwdGVyLTI2Ny8=",
      "date": "3 bulan yang lalu"
    },
    {
      "chapter": "266",
      "title": "Komik Age of Terror Chapter 266",
      "url": "b64:aHR0cHM6Ly9rb21pa2luZG8uY2gvYWdlLW9mLXRlcnJvci1jaGFwdGVyLTI2Ni8=",
      "date": "3 bulan yang lalu"
    },
    {
      "chapter": "265",
      "title": "Komik Age of Terror Chapter 265",
      "url": "b64:aHR0cHM6Ly9rb21pa2luZG8uY2gvYWdlLW9mLXRlcnJvci1jaGFwdGVyLTI2NS8=",
      "date": "3 bulan yang lalu"
    },
    {
      "chapter": "264",
      "title": "Komik Age of Terror Chapter 264",
      "url": "b64:aHR0cHM6Ly9rb21pa2luZG8uY2gvYWdlLW9mLXRlcnJvci1jaGFwdGVyLTI2NC8=",
      "date": "3 bulan yang lalu"
    },
    {
      "chapter": "263",
      "title": "Komik Age of Terror Chapter 263",
      "url": "b64:aHR0cHM6Ly9rb21pa2luZG8uY2gvYWdlLW9mLXRlcnJvci1jaGFwdGVyLTI2My8=",
      "date": "3 bulan yang lalu"
    },
    {
      "chapter": "262",
      "title": "Komik Age of Terror Chapter 262",
      "url": "b64:aHR0cHM6Ly9rb21pa2luZG8uY2gvYWdlLW9mLXRlcnJvci1jaGFwdGVyLTI2Mi8=",
      "date": "3 bulan yang lalu"
    },
    {
      "chapter": "261",
      "title": "Komik Age of Terror Chapter 261",
      "url": "b64:aHR0cHM6Ly9rb21pa2luZG8uY2gvYWdlLW9mLXRlcnJvci1jaGFwdGVyLTI2MS8=",
      "date": "3 bulan yang lalu"
    },
    {
      "chapter": "260",
      "title": "Komik Age of Terror Chapter 260",
      "url": "b64:aHR0cHM6Ly9rb21pa2luZG8uY2gvYWdlLW9mLXRlcnJvci1jaGFwdGVyLTI2MC8=",
      "date": "3 bulan yang lalu"
    },
    {
      "chapter": "259",
      "title": "Komik Age of Terror Chapter 259",
      "url": "b64:aHR0cHM6Ly9rb21pa2luZG8uY2gvYWdlLW9mLXRlcnJvci1jaGFwdGVyLTI1OS8=",
      "date": "3 bulan yang lalu"
    },
    {
      "chapter": "258",
      "title": "Komik Age of Terror Chapter 258",
      "url": "b64:aHR0cHM6Ly9rb21pa2luZG8uY2gvYWdlLW9mLXRlcnJvci1jaGFwdGVyLTI1OC8=",
      "date": "3 bulan yang lalu"
    },
    {
      "chapter": "257",
      "title": "Komik Age of Terror Chapter 257",
      "url": "b64:aHR0cHM6Ly9rb21pa2luZG8uY2gvYWdlLW9mLXRlcnJvci1jaGFwdGVyLTI1Ny8=",
      "date": "3 bulan yang lalu"
    },
    {
      "chapter": "256",
      "title": "Komik Age of Terror Chapter 256",
      "url": "b64:aHR0cHM6Ly9rb21pa2luZG8uY2gvYWdlLW9mLXRlcnJvci1jaGFwdGVyLTI1Ni8=",
      "date": "3 bulan yang lalu"
    },
    {
      "chapter": "255",
      "title": "Komik Age of Terror Chapter 255",
      "url": "b64:aHR0cHM6Ly9rb21pa2luZG8uY2gvYWdlLW9mLXRlcnJvci1jaGFwdGVyLTI1NS8=",
      "date": "3 bulan yang lalu"
    },
    {
      "chapter": "254",
      "title": "Komik Age of Terror Chapter 254",
      "url": "b64:aHR0cHM6Ly9rb21pa2luZG8uY2gvYWdlLW9mLXRlcnJvci1jaGFwdGVyLTI1NC8=",
      "date": "3 bulan yang lalu"
    },
    {
      "chapter": "253",
      "title": "Komik Age of Terror Chapter 253",
      "url": "b64:aHR0cHM6Ly9rb21pa2luZG8uY2gvYWdlLW9mLXRlcnJvci1jaGFwdGVyLTI1My8=",
      "date": "4 bulan yang lalu"
    },
    {
      "chapter": "252",
      "title": "Komik Age of Terror Chapter 252",
      "url": "b64:aHR0cHM6Ly9rb21pa2luZG8uY2gvYWdlLW9mLXRlcnJvci1jaGFwdGVyLTI1Mi8=",
      "date": "4 bulan yang lalu"
    },
    {
      "chapter": "251",
      "title": "Komik Age of Terror Chapter 251",
      "url": "b64:aHR0cHM6Ly9rb21pa2luZG8uY2gvYWdlLW9mLXRlcnJvci1jaGFwdGVyLTI1MS8=",
      "date": "4 bulan yang lalu"
    },
    {
      "chapter": "250",
      "title": "Komik Age of Terror Chapter 250",
      "url": "b64:aHR0cHM6Ly9rb21pa2luZG8uY2gvYWdlLW9mLXRlcnJvci1jaGFwdGVyLTI1MC8=",
      "date": "4 bulan yang lalu"
    },
    {
      "chapter": "249",
      "title": "Komik Age of Terror Chapter 249",
      "url": "b64:aHR0cHM6Ly9rb21pa2luZG8uY2gvYWdlLW9mLXRlcnJvci1jaGFwdGVyLTI0OS8=",
      "date": "4 bulan yang lalu"
    },
    {
      "chapter": "248",
      "title": "Komik Age of Terror Chapter 248",
      "url": "b64:aHR0cHM6Ly9rb21pa2luZG8uY2gvYWdlLW9mLXRlcnJvci1jaGFwdGVyLTI0OC8=",
      "date": "4 bulan yang lalu"
    },
    {
      "chapter": "247",
      "title": "Komik Age of Terror Chapter 247",
      "url": "b64:aHR0cHM6Ly9rb21pa2luZG8uY2gvYWdlLW9mLXRlcnJvci1jaGFwdGVyLTI0Ny8=",
      "date": "4 bulan yang lalu"
    },
    {
      "chapter": "246",
      "title": "Komik Age of Terror Chapter 246",
      "url": "b64:aHR0cHM6Ly9rb21pa2luZG8uY2gvYWdlLW9mLXRlcnJvci1jaGFwdGVyLTI0Ni8=",
      "date": "4 bulan yang lalu"
    },
    {
      "chapter": "245",
      "title": "Komik Age of Terror Chapter 245",
      "url": "b64:aHR0cHM6Ly9rb21pa2luZG8uY2gvYWdlLW9mLXRlcnJvci1jaGFwdGVyLTI0NS8=",
      "date": "4 bulan yang lalu"
    },
    {
      "chapter": "244",
      "title": "Komik Age of Terror Chapter 244",
      "url": "b64:aHR0cHM6Ly9rb21pa2luZG8uY2gvYWdlLW9mLXRlcnJvci1jaGFwdGVyLTI0NC8=",
      "date": "4 bulan yang lalu"
    },
    {
      "chapter": "243",
      "title": "Komik Age of Terror Chapter 243",
      "url": "b64:aHR0cHM6Ly9rb21pa2luZG8uY2gvYWdlLW9mLXRlcnJvci1jaGFwdGVyLTI0My8=",
      "date": "4 bulan yang lalu"
    },
    {
      "chapter": "242",
      "title": "Komik Age of Terror Chapter 242",
      "url": "b64:aHR0cHM6Ly9rb21pa2luZG8uY2gvYWdlLW9mLXRlcnJvci1jaGFwdGVyLTI0Mi8=",
      "date": "4 bulan yang lalu"
    },
    {
      "chapter": "241",
      "title": "Komik Age of Terror Chapter 241",
      "url": "b64:aHR0cHM6Ly9rb21pa2luZG8uY2gvYWdlLW9mLXRlcnJvci1jaGFwdGVyLTI0MS8=",
      "date": "4 bulan yang lalu"
    },
    {
      "chapter": "240",
      "title": "Komik Age of Terror Chapter 240",
      "url": "b64:aHR0cHM6Ly9rb21pa2luZG8uY2gvYWdlLW9mLXRlcnJvci1jaGFwdGVyLTI0MC8=",
      "date": "4 bulan yang lalu"
    },
    {
      "chapter": "239",
      "title": "Komik Age of Terror Chapter 239",
      "url": "b64:aHR0cHM6Ly9rb21pa2luZG8uY2gvYWdlLW9mLXRlcnJvci1jaGFwdGVyLTIzOS8=",
      "date": "4 bulan yang lalu"
    },
    {
      "chapter": "238",
      "title": "Komik Age of Terror Chapter 238",
      "url": "b64:aHR0cHM6Ly9rb21pa2luZG8uY2gvYWdlLW9mLXRlcnJvci1jaGFwdGVyLTIzOC8=",
      "date": "4 bulan yang lalu"
    },
    {
      "chapter": "237",
      "title": "Komik Age of Terror Chapter 237",
      "url": "b64:aHR0cHM6Ly9rb21pa2luZG8uY2gvYWdlLW9mLXRlcnJvci1jaGFwdGVyLTIzNy8=",
      "date": "4 bulan yang lalu"
    },
    {
      "chapter": "236",
      "title": "Komik Age of Terror Chapter 236",
      "url": "b64:aHR0cHM6Ly9rb21pa2luZG8uY2gvYWdlLW9mLXRlcnJvci1jaGFwdGVyLTIzNi8=",
      "date": "4 bulan yang lalu"
    },
    {
      "chapter": "235",
      "title": "Komik Age of Terror Chapter 235",
      "url": "b64:aHR0cHM6Ly9rb21pa2luZG8uY2gvYWdlLW9mLXRlcnJvci1jaGFwdGVyLTIzNS8=",
      "date": "4 bulan yang lalu"
    },
    {
      "chapter": "234",
      "title": "Komik Age of Terror Chapter 234",
      "url": "b64:aHR0cHM6Ly9rb21pa2luZG8uY2gvYWdlLW9mLXRlcnJvci1jaGFwdGVyLTIzNC8=",
      "date": "4 bulan yang lalu"
    },
    {
      "chapter": "233",
      "title": "Komik Age of Terror Chapter 233",
      "url": "b64:aHR0cHM6Ly9rb21pa2luZG8uY2gvYWdlLW9mLXRlcnJvci1jaGFwdGVyLTIzMy8=",
      "date": "4 bulan yang lalu"
    },
    {
      "chapter": "232",
      "title": "Komik Age of Terror Chapter 232",
      "url": "b64:aHR0cHM6Ly9rb21pa2luZG8uY2gvYWdlLW9mLXRlcnJvci1jaGFwdGVyLTIzMi8=",
      "date": "4 bulan yang lalu"
    },
    {
      "chapter": "231",
      "title": "Komik Age of Terror Chapter 231",
      "url": "b64:aHR0cHM6Ly9rb21pa2luZG8uY2gvYWdlLW9mLXRlcnJvci1jaGFwdGVyLTIzMS8=",
      "date": "4 bulan yang lalu"
    },
    {
      "chapter": "230",
      "title": "Komik Age of Terror Chapter 230",
      "url": "b64:aHR0cHM6Ly9rb21pa2luZG8uY2gvYWdlLW9mLXRlcnJvci1jaGFwdGVyLTIzMC8=",
      "date": "5 bulan yang lalu"
    },
    {
      "chapter": "229",
      "title": "Komik Age of Terror Chapter 229",
      "url": "b64:aHR0cHM6Ly9rb21pa2luZG8uY2gvYWdlLW9mLXRlcnJvci1jaGFwdGVyLTIyOS8=",
      "date": "5 bulan yang lalu"
    },
    {
      "chapter": "228",
      "title": "Komik Age of Terror Chapter 228",
      "url": "b64:aHR0cHM6Ly9rb21pa2luZG8uY2gvYWdlLW9mLXRlcnJvci1jaGFwdGVyLTIyOC8=",
      "date": "2 tahun yang lalu"
    },
    {
      "chapter": "227",
      "title": "Komik Age of Terror Chapter 227",
      "url": "b64:aHR0cHM6Ly9rb21pa2luZG8uY2gvYWdlLW9mLXRlcnJvci1jaGFwdGVyLTIyNy8=",
      "date": "2 tahun yang lalu"
    },
    {
      "chapter": "226",
      "title": "Komik Age of Terror Chapter 226",
      "url": "b64:aHR0cHM6Ly9rb21pa2luZG8uY2gvYWdlLW9mLXRlcnJvci1jaGFwdGVyLTIyNi8=",
      "date": "2 tahun yang lalu"
    },
    {
      "chapter": "225",
      "title": "Komik Age of Terror Chapter 225",
      "url": "b64:aHR0cHM6Ly9rb21pa2luZG8uY2gvYWdlLW9mLXRlcnJvci1jaGFwdGVyLTIyNS8=",
      "date": "2 tahun yang lalu"
    },
    {
      "chapter": "224",
      "title": "Komik Age of Terror Chapter 224",
      "url": "b64:aHR0cHM6Ly9rb21pa2luZG8uY2gvYWdlLW9mLXRlcnJvci1jaGFwdGVyLTIyNC8=",
      "date": "2 tahun yang lalu"
    },
    {
      "chapter": "223",
      "title": "Komik Age of Terror Chapter 223",
      "url": "b64:aHR0cHM6Ly9rb21pa2luZG8uY2gvYWdlLW9mLXRlcnJvci1jaGFwdGVyLTIyMy8=",
      "date": "2 tahun yang lalu"
    },
    {
      "chapter": "222",
      "title": "Komik Age of Terror Chapter 222",
      "url": "b64:aHR0cHM6Ly9rb21pa2luZG8uY2gvYWdlLW9mLXRlcnJvci1jaGFwdGVyLTIyMi8=",
      "date": "2 tahun yang lalu"
    },
    {
      "chapter": "221",
      "title": "Komik Age of Terror Chapter 221",
      "url": "b64:aHR0cHM6Ly9rb21pa2luZG8uY2gvYWdlLW9mLXRlcnJvci1jaGFwdGVyLTIyMS8=",
      "date": "2 tahun yang lalu"
    },
    {
      "chapter": "220",
      "title": "Komik Age of Terror Chapter 220",
      "url": "b64:aHR0cHM6Ly9rb21pa2luZG8uY2gvYWdlLW9mLXRlcnJvci1jaGFwdGVyLTIyMC8=",
      "date": "2 tahun yang lalu"
    },
    {
      "chapter": "219",
      "title": "Komik Age of Terror Chapter 219",
      "url": "b64:aHR0cHM6Ly9rb21pa2luZG8uY2gvYWdlLW9mLXRlcnJvci1jaGFwdGVyLTIxOS8=",
      "date": "2 tahun yang lalu"
    },
    {
      "chapter": "218",
      "title": "Komik Age of Terror Chapter 218",
      "url": "b64:aHR0cHM6Ly9rb21pa2luZG8uY2gvYWdlLW9mLXRlcnJvci1jaGFwdGVyLTIxOC8=",
      "date": "2 tahun yang lalu"
    },
    {
      "chapter": "217",
      "title": "Komik Age of Terror Chapter 217",
      "url": "b64:aHR0cHM6Ly9rb21pa2luZG8uY2gvYWdlLW9mLXRlcnJvci1jaGFwdGVyLTIxNy8=",
      "date": "2 tahun yang lalu"
    },
    {
      "chapter": "216",
      "title": "Komik Age of Terror Chapter 216",
      "url": "b64:aHR0cHM6Ly9rb21pa2luZG8uY2gvYWdlLW9mLXRlcnJvci1jaGFwdGVyLTIxNi8=",
      "date": "2 tahun yang lalu"
    },
    {
      "chapter": "215",
      "title": "Komik Age of Terror Chapter 215",
      "url": "b64:aHR0cHM6Ly9rb21pa2luZG8uY2gvYWdlLW9mLXRlcnJvci1jaGFwdGVyLTIxNS8=",
      "date": "2 tahun yang lalu"
    },
    {
      "chapter": "214",
      "title": "Komik Age of Terror Chapter 214",
      "url": "b64:aHR0cHM6Ly9rb21pa2luZG8uY2gvYWdlLW9mLXRlcnJvci1jaGFwdGVyLTIxNC8=",
      "date": "2 tahun yang lalu"
    },
    {
      "chapter": "213",
      "title": "Komik Age of Terror Chapter 213",
      "url": "b64:aHR0cHM6Ly9rb21pa2luZG8uY2gvYWdlLW9mLXRlcnJvci1jaGFwdGVyLTIxMy8=",
      "date": "2 tahun yang lalu"
    },
    {
      "chapter": "212",
      "title": "Komik Age of Terror Chapter 212",
      "url": "b64:aHR0cHM6Ly9rb21pa2luZG8uY2gvYWdlLW9mLXRlcnJvci1jaGFwdGVyLTIxMi8=",
      "date": "2 tahun yang lalu"
    },
    {
      "chapter": "211",
      "title": "Komik Age of Terror Chapter 211",
      "url": "b64:aHR0cHM6Ly9rb21pa2luZG8uY2gvYWdlLW9mLXRlcnJvci1jaGFwdGVyLTIxMS8=",
      "date": "2 tahun yang lalu"
    },
    {
      "chapter": "210",
      "title": "Komik Age of Terror Chapter 210",
      "url": "b64:aHR0cHM6Ly9rb21pa2luZG8uY2gvYWdlLW9mLXRlcnJvci1jaGFwdGVyLTIxMC8=",
      "date": "2 tahun yang lalu"
    },
    {
      "chapter": "209",
      "title": "Komik Age of Terror Chapter 209",
      "url": "b64:aHR0cHM6Ly9rb21pa2luZG8uY2gvYWdlLW9mLXRlcnJvci1jaGFwdGVyLTIwOS8=",
      "date": "2 tahun yang lalu"
    },
    {
      "chapter": "208",
      "title": "Komik Age of Terror Chapter 208",
      "url": "b64:aHR0cHM6Ly9rb21pa2luZG8uY2gvYWdlLW9mLXRlcnJvci1jaGFwdGVyLTIwOC8=",
      "date": "2 tahun yang lalu"
    },
    {
      "chapter": "207",
      "title": "Komik Age of Terror Chapter 207",
      "url": "b64:aHR0cHM6Ly9rb21pa2luZG8uY2gvYWdlLW9mLXRlcnJvci1jaGFwdGVyLTIwNy8=",
      "date": "2 tahun yang lalu"
    },
    {
      "chapter": "206",
      "title": "Komik Age of Terror Chapter 206",
      "url": "b64:aHR0cHM6Ly9rb21pa2luZG8uY2gvYWdlLW9mLXRlcnJvci1jaGFwdGVyLTIwNi8=",
      "date": "2 tahun yang lalu"
    },
    {
      "chapter": "205",
      "title": "Komik Age of Terror Chapter 205",
      "url": "b64:aHR0cHM6Ly9rb21pa2luZG8uY2gvYWdlLW9mLXRlcnJvci1jaGFwdGVyLTIwNS8=",
      "date": "2 tahun yang lalu"
    },
    {
      "chapter": "204",
      "title": "Komik Age of Terror Chapter 204",
      "url": "b64:aHR0cHM6Ly9rb21pa2luZG8uY2gvYWdlLW9mLXRlcnJvci1jaGFwdGVyLTIwNC8=",
      "date": "2 tahun yang lalu"
    },
    {
      "chapter": "203",
      "title": "Komik Age of Terror Chapter 203",
      "url": "b64:aHR0cHM6Ly9rb21pa2luZG8uY2gvYWdlLW9mLXRlcnJvci1jaGFwdGVyLTIwMy8=",
      "date": "2 tahun yang lalu"
    },
    {
      "chapter": "202",
      "title": "Komik Age of Terror Chapter 202",
      "url": "b64:aHR0cHM6Ly9rb21pa2luZG8uY2gvYWdlLW9mLXRlcnJvci1jaGFwdGVyLTIwMi8=",
      "date": "2 tahun yang lalu"
    },
    {
      "chapter": "201",
      "title": "Komik Age of Terror Chapter 201",
      "url": "b64:aHR0cHM6Ly9rb21pa2luZG8uY2gvYWdlLW9mLXRlcnJvci1jaGFwdGVyLTIwMS8=",
      "date": "2 tahun yang lalu"
    },
    {
      "chapter": "200",
      "title": "Komik Age of Terror Chapter 200",
      "url": "b64:aHR0cHM6Ly9rb21pa2luZG8uY2gvYWdlLW9mLXRlcnJvci1jaGFwdGVyLTIwMC8=",
      "date": "2 tahun yang lalu"
    },
    {
      "chapter": "199",
      "title": "Komik Age of Terror Chapter 199",
      "url": "b64:aHR0cHM6Ly9rb21pa2luZG8uY2gvYWdlLW9mLXRlcnJvci1jaGFwdGVyLTE5OS8=",
      "date": "2 tahun yang lalu"
    },
    {
      "chapter": "198",
      "title": "Komik Age of Terror Chapter 198",
      "url": "b64:aHR0cHM6Ly9rb21pa2luZG8uY2gvYWdlLW9mLXRlcnJvci1jaGFwdGVyLTE5OC8=",
      "date": "2 tahun yang lalu"
    },
    {
      "chapter": "197",
      "title": "Komik Age of Terror Chapter 197",
      "url": "b64:aHR0cHM6Ly9rb21pa2luZG8uY2gvYWdlLW9mLXRlcnJvci1jaGFwdGVyLTE5Ny8=",
      "date": "2 tahun yang lalu"
    },
    {
      "chapter": "196",
      "title": "Komik Age of Terror Chapter 196",
      "url": "b64:aHR0cHM6Ly9rb21pa2luZG8uY2gvYWdlLW9mLXRlcnJvci1jaGFwdGVyLTE5Ni8=",
      "date": "2 tahun yang lalu"
    },
    {
      "chapter": "195",
      "title": "Komik Age of Terror Chapter 195",
      "url": "b64:aHR0cHM6Ly9rb21pa2luZG8uY2gvYWdlLW9mLXRlcnJvci1jaGFwdGVyLTE5NS8=",
      "date": "2 tahun yang lalu"
    },
    {
      "chapter": "194",
      "title": "Komik Age of Terror Chapter 194",
      "url": "b64:aHR0cHM6Ly9rb21pa2luZG8uY2gvYWdlLW9mLXRlcnJvci1jaGFwdGVyLTE5NC8=",
      "date": "2 tahun yang lalu"
    },
    {
      "chapter": "193",
      "title": "Komik Age of Terror Chapter 193",
      "url": "b64:aHR0cHM6Ly9rb21pa2luZG8uY2gvYWdlLW9mLXRlcnJvci1jaGFwdGVyLTE5My8=",
      "date": "2 tahun yang lalu"
    },
    {
      "chapter": "192",
      "title": "Komik Age of Terror Chapter 192",
      "url": "b64:aHR0cHM6Ly9rb21pa2luZG8uY2gvYWdlLW9mLXRlcnJvci1jaGFwdGVyLTE5Mi8=",
      "date": "2 tahun yang lalu"
    },
    {
      "chapter": "191",
      "title": "Komik Age of Terror Chapter 191",
      "url": "b64:aHR0cHM6Ly9rb21pa2luZG8uY2gvYWdlLW9mLXRlcnJvci1jaGFwdGVyLTE5MS8=",
      "date": "2 tahun yang lalu"
    },
    {
      "chapter": "190",
      "title": "Komik Age of Terror Chapter 190",
      "url": "b64:aHR0cHM6Ly9rb21pa2luZG8uY2gvYWdlLW9mLXRlcnJvci1jaGFwdGVyLTE5MC8=",
      "date": "2 tahun yang lalu"
    },
    {
      "chapter": "189",
      "title": "Komik Age of Terror Chapter 189",
      "url": "b64:aHR0cHM6Ly9rb21pa2luZG8uY2gvYWdlLW9mLXRlcnJvci1jaGFwdGVyLTE4OS8=",
      "date": "2 tahun yang lalu"
    },
    {
      "chapter": "188",
      "title": "Komik Age of Terror Chapter 188",
      "url": "b64:aHR0cHM6Ly9rb21pa2luZG8uY2gvYWdlLW9mLXRlcnJvci1jaGFwdGVyLTE4OC8=",
      "date": "2 tahun yang lalu"
    },
    {
      "chapter": "187",
      "title": "Komik Age of Terror Chapter 187",
      "url": "b64:aHR0cHM6Ly9rb21pa2luZG8uY2gvYWdlLW9mLXRlcnJvci1jaGFwdGVyLTE4Ny8=",
      "date": "2 tahun yang lalu"
    },
    {
      "chapter": "186",
      "title": "Komik Age of Terror Chapter 186",
      "url": "b64:aHR0cHM6Ly9rb21pa2luZG8uY2gvYWdlLW9mLXRlcnJvci1jaGFwdGVyLTE4Ni8=",
      "date": "2 tahun yang lalu"
    },
    {
      "chapter": "185",
      "title": "Komik Age of Terror Chapter 185",
      "url": "b64:aHR0cHM6Ly9rb21pa2luZG8uY2gvYWdlLW9mLXRlcnJvci1jaGFwdGVyLTE4NS8=",
      "date": "2 tahun yang lalu"
    },
    {
      "chapter": "184",
      "title": "Komik Age of Terror Chapter 184",
      "url": "b64:aHR0cHM6Ly9rb21pa2luZG8uY2gvYWdlLW9mLXRlcnJvci1jaGFwdGVyLTE4NC8=",
      "date": "2 tahun yang lalu"
    },
    {
      "chapter": "183",
      "title": "Komik Age of Terror Chapter 183",
      "url": "b64:aHR0cHM6Ly9rb21pa2luZG8uY2gvYWdlLW9mLXRlcnJvci1jaGFwdGVyLTE4My8=",
      "date": "2 tahun yang lalu"
    },
    {
      "chapter": "182",
      "title": "Komik Age of Terror Chapter 182",
      "url": "b64:aHR0cHM6Ly9rb21pa2luZG8uY2gvYWdlLW9mLXRlcnJvci1jaGFwdGVyLTE4Mi8=",
      "date": "2 tahun yang lalu"
    },
    {
      "chapter": "181",
      "title": "Komik Age of Terror Chapter 181",
      "url": "b64:aHR0cHM6Ly9rb21pa2luZG8uY2gvYWdlLW9mLXRlcnJvci1jaGFwdGVyLTE4MS8=",
      "date": "2 tahun yang lalu"
    },
    {
      "chapter": "180",
      "title": "Komik Age of Terror Chapter 180",
      "url": "b64:aHR0cHM6Ly9rb21pa2luZG8uY2gvYWdlLW9mLXRlcnJvci1jaGFwdGVyLTE4MC8=",
      "date": "2 tahun yang lalu"
    },
    {
      "chapter": "179",
      "title": "Komik Age of Terror Chapter 179",
      "url": "b64:aHR0cHM6Ly9rb21pa2luZG8uY2gvYWdlLW9mLXRlcnJvci1jaGFwdGVyLTE3OS8=",
      "date": "2 tahun yang lalu"
    },
    {
      "chapter": "178",
      "title": "Komik Age of Terror Chapter 178",
      "url": "b64:aHR0cHM6Ly9rb21pa2luZG8uY2gvYWdlLW9mLXRlcnJvci1jaGFwdGVyLTE3OC8=",
      "date": "2 tahun yang lalu"
    },
    {
      "chapter": "177",
      "title": "Komik Age of Terror Chapter 177",
      "url": "b64:aHR0cHM6Ly9rb21pa2luZG8uY2gvYWdlLW9mLXRlcnJvci1jaGFwdGVyLTE3Ny8=",
      "date": "2 tahun yang lalu"
    },
    {
      "chapter": "176",
      "title": "Komik Age of Terror Chapter 176",
      "url": "b64:aHR0cHM6Ly9rb21pa2luZG8uY2gvYWdlLW9mLXRlcnJvci1jaGFwdGVyLTE3Ni8=",
      "date": "2 tahun yang lalu"
    },
    {
      "chapter": "175",
      "title": "Komik Age of Terror Chapter 175",
      "url": "b64:aHR0cHM6Ly9rb21pa2luZG8uY2gvYWdlLW9mLXRlcnJvci1jaGFwdGVyLTE3NS8=",
      "date": "2 tahun yang lalu"
    },
    {
      "chapter": "174",
      "title": "Komik Age of Terror Chapter 174",
      "url": "b64:aHR0cHM6Ly9rb21pa2luZG8uY2gvYWdlLW9mLXRlcnJvci1jaGFwdGVyLTE3NC8=",
      "date": "2 tahun yang lalu"
    },
    {
      "chapter": "173",
      "title": "Komik Age of Terror Chapter 173",
      "url": "b64:aHR0cHM6Ly9rb21pa2luZG8uY2gvYWdlLW9mLXRlcnJvci1jaGFwdGVyLTE3My8=",
      "date": "2 tahun yang lalu"
    },
    {
      "chapter": "172",
      "title": "Komik Age of Terror Chapter 172",
      "url": "b64:aHR0cHM6Ly9rb21pa2luZG8uY2gvYWdlLW9mLXRlcnJvci1jaGFwdGVyLTE3Mi8=",
      "date": "2 tahun yang lalu"
    },
    {
      "chapter": "171",
      "title": "Komik Age of Terror Chapter 171",
      "url": "b64:aHR0cHM6Ly9rb21pa2luZG8uY2gvYWdlLW9mLXRlcnJvci1jaGFwdGVyLTE3MS8=",
      "date": "2 tahun yang lalu"
    },
    {
      "chapter": "170",
      "title": "Komik Age of Terror Chapter 170",
      "url": "b64:aHR0cHM6Ly9rb21pa2luZG8uY2gvYWdlLW9mLXRlcnJvci1jaGFwdGVyLTE3MC8=",
      "date": "2 tahun yang lalu"
    },
    {
      "chapter": "169",
      "title": "Komik Age of Terror Chapter 169",
      "url": "b64:aHR0cHM6Ly9rb21pa2luZG8uY2gvYWdlLW9mLXRlcnJvci1jaGFwdGVyLTE2OS8=",
      "date": "2 tahun yang lalu"
    },
    {
      "chapter": "168",
      "title": "Komik Age of Terror Chapter 168",
      "url": "b64:aHR0cHM6Ly9rb21pa2luZG8uY2gvYWdlLW9mLXRlcnJvci1jaGFwdGVyLTE2OC8=",
      "date": "2 tahun yang lalu"
    },
    {
      "chapter": "167",
      "title": "Komik Age of Terror Chapter 167",
      "url": "b64:aHR0cHM6Ly9rb21pa2luZG8uY2gvYWdlLW9mLXRlcnJvci1jaGFwdGVyLTE2Ny8=",
      "date": "2 tahun yang lalu"
    },
    {
      "chapter": "166",
      "title": "Komik Age of Terror Chapter 166",
      "url": "b64:aHR0cHM6Ly9rb21pa2luZG8uY2gvYWdlLW9mLXRlcnJvci1jaGFwdGVyLTE2Ni8=",
      "date": "2 tahun yang lalu"
    },
    {
      "chapter": "165",
      "title": "Komik Age of Terror Chapter 165",
      "url": "b64:aHR0cHM6Ly9rb21pa2luZG8uY2gvYWdlLW9mLXRlcnJvci1jaGFwdGVyLTE2NS8=",
      "date": "2 tahun yang lalu"
    },
    {
      "chapter": "164",
      "title": "Komik Age of Terror Chapter 164",
      "url": "b64:aHR0cHM6Ly9rb21pa2luZG8uY2gvYWdlLW9mLXRlcnJvci1jaGFwdGVyLTE2NC8=",
      "date": "2 tahun yang lalu"
    },
    {
      "chapter": "163",
      "title": "Komik Age of Terror Chapter 163",
      "url": "b64:aHR0cHM6Ly9rb21pa2luZG8uY2gvYWdlLW9mLXRlcnJvci1jaGFwdGVyLTE2My8=",
      "date": "2 tahun yang lalu"
    },
    {
      "chapter": "162",
      "title": "Komik Age of Terror Chapter 162",
      "url": "b64:aHR0cHM6Ly9rb21pa2luZG8uY2gvYWdlLW9mLXRlcnJvci1jaGFwdGVyLTE2Mi8=",
      "date": "2 tahun yang lalu"
    },
    {
      "chapter": "161",
      "title": "Komik Age of Terror Chapter 161",
      "url": "b64:aHR0cHM6Ly9rb21pa2luZG8uY2gvYWdlLW9mLXRlcnJvci1jaGFwdGVyLTE2MS8=",
      "date": "2 tahun yang lalu"
    },
    {
      "chapter": "160",
      "title": "Komik Age of Terror Chapter 160",
      "url": "b64:aHR0cHM6Ly9rb21pa2luZG8uY2gvYWdlLW9mLXRlcnJvci1jaGFwdGVyLTE2MC8=",
      "date": "2 tahun yang lalu"
    },
    {
      "chapter": "159",
      "title": "Komik Age of Terror Chapter 159",
      "url": "b64:aHR0cHM6Ly9rb21pa2luZG8uY2gvYWdlLW9mLXRlcnJvci1jaGFwdGVyLTE1OS8=",
      "date": "2 tahun yang lalu"
    },
    {
      "chapter": "158",
      "title": "Komik Age of Terror Chapter 158",
      "url": "b64:aHR0cHM6Ly9rb21pa2luZG8uY2gvYWdlLW9mLXRlcnJvci1jaGFwdGVyLTE1OC8=",
      "date": "2 tahun yang lalu"
    },
    {
      "chapter": "157",
      "title": "Komik Age of Terror Chapter 157",
      "url": "b64:aHR0cHM6Ly9rb21pa2luZG8uY2gvYWdlLW9mLXRlcnJvci1jaGFwdGVyLTE1Ny8=",
      "date": "2 tahun yang lalu"
    },
    {
      "chapter": "156",
      "title": "Komik Age of Terror Chapter 156",
      "url": "b64:aHR0cHM6Ly9rb21pa2luZG8uY2gvYWdlLW9mLXRlcnJvci1jaGFwdGVyLTE1Ni8=",
      "date": "2 tahun yang lalu"
    },
    {
      "chapter": "155",
      "title": "Komik Age of Terror Chapter 155",
      "url": "b64:aHR0cHM6Ly9rb21pa2luZG8uY2gvYWdlLW9mLXRlcnJvci1jaGFwdGVyLTE1NS8=",
      "date": "2 tahun yang lalu"
    },
    {
      "chapter": "154",
      "title": "Komik Age of Terror Chapter 154",
      "url": "b64:aHR0cHM6Ly9rb21pa2luZG8uY2gvYWdlLW9mLXRlcnJvci1jaGFwdGVyLTE1NC8=",
      "date": "2 tahun yang lalu"
    },
    {
      "chapter": "153",
      "title": "Komik Age of Terror Chapter 153",
      "url": "b64:aHR0cHM6Ly9rb21pa2luZG8uY2gvYWdlLW9mLXRlcnJvci1jaGFwdGVyLTE1My8=",
      "date": "2 tahun yang lalu"
    },
    {
      "chapter": "152",
      "title": "Komik Age of Terror Chapter 152",
      "url": "b64:aHR0cHM6Ly9rb21pa2luZG8uY2gvYWdlLW9mLXRlcnJvci1jaGFwdGVyLTE1Mi8=",
      "date": "2 tahun yang lalu"
    },
    {
      "chapter": "151",
      "title": "Komik Age of Terror Chapter 151",
      "url": "b64:aHR0cHM6Ly9rb21pa2luZG8uY2gvYWdlLW9mLXRlcnJvci1jaGFwdGVyLTE1MS8=",
      "date": "2 tahun yang lalu"
    },
    {
      "chapter": "150",
      "title": "Komik Age of Terror Chapter 150",
      "url": "b64:aHR0cHM6Ly9rb21pa2luZG8uY2gvYWdlLW9mLXRlcnJvci1jaGFwdGVyLTE1MC8=",
      "date": "2 tahun yang lalu"
    },
    {
      "chapter": "149",
      "title": "Komik Age of Terror Chapter 149",
      "url": "b64:aHR0cHM6Ly9rb21pa2luZG8uY2gvYWdlLW9mLXRlcnJvci1jaGFwdGVyLTE0OS8=",
      "date": "2 tahun yang lalu"
    },
    {
      "chapter": "148",
      "title": "Komik Age of Terror Chapter 148",
      "url": "b64:aHR0cHM6Ly9rb21pa2luZG8uY2gvYWdlLW9mLXRlcnJvci1jaGFwdGVyLTE0OC8=",
      "date": "2 tahun yang lalu"
    },
    {
      "chapter": "147",
      "title": "Komik Age of Terror Chapter 147",
      "url": "b64:aHR0cHM6Ly9rb21pa2luZG8uY2gvYWdlLW9mLXRlcnJvci1jaGFwdGVyLTE0Ny8=",
      "date": "2 tahun yang lalu"
    },
    {
      "chapter": "146",
      "title": "Komik Age of Terror Chapter 146",
      "url": "b64:aHR0cHM6Ly9rb21pa2luZG8uY2gvYWdlLW9mLXRlcnJvci1jaGFwdGVyLTE0Ni8=",
      "date": "2 tahun yang lalu"
    },
    {
      "chapter": "145",
      "title": "Komik Age of Terror Chapter 145",
      "url": "b64:aHR0cHM6Ly9rb21pa2luZG8uY2gvYWdlLW9mLXRlcnJvci1jaGFwdGVyLTE0NS8=",
      "date": "2 tahun yang lalu"
    },
    {
      "chapter": "144",
      "title": "Komik Age of Terror Chapter 144",
      "url": "b64:aHR0cHM6Ly9rb21pa2luZG8uY2gvYWdlLW9mLXRlcnJvci1jaGFwdGVyLTE0NC8=",
      "date": "2 tahun yang lalu"
    },
    {
      "chapter": "143",
      "title": "Komik Age of Terror Chapter 143",
      "url": "b64:aHR0cHM6Ly9rb21pa2luZG8uY2gvYWdlLW9mLXRlcnJvci1jaGFwdGVyLTE0My8=",
      "date": "2 tahun yang lalu"
    },
    {
      "chapter": "142",
      "title": "Komik Age of Terror Chapter 142",
      "url": "b64:aHR0cHM6Ly9rb21pa2luZG8uY2gvYWdlLW9mLXRlcnJvci1jaGFwdGVyLTE0Mi8=",
      "date": "2 tahun yang lalu"
    },
    {
      "chapter": "141",
      "title": "Komik Age of Terror Chapter 141",
      "url": "b64:aHR0cHM6Ly9rb21pa2luZG8uY2gvYWdlLW9mLXRlcnJvci1jaGFwdGVyLTE0MS8=",
      "date": "2 tahun yang lalu"
    },
    {
      "chapter": "140",
      "title": "Komik Age of Terror Chapter 140",
      "url": "b64:aHR0cHM6Ly9rb21pa2luZG8uY2gvYWdlLW9mLXRlcnJvci1jaGFwdGVyLTE0MC8=",
      "date": "2 tahun yang lalu"
    },
    {
      "chapter": "139",
      "title": "Komik Age of Terror Chapter 139",
      "url": "b64:aHR0cHM6Ly9rb21pa2luZG8uY2gvYWdlLW9mLXRlcnJvci1jaGFwdGVyLTEzOS8=",
      "date": "2 tahun yang lalu"
    },
    {
      "chapter": "138",
      "title": "Komik Age of Terror Chapter 138",
      "url": "b64:aHR0cHM6Ly9rb21pa2luZG8uY2gvYWdlLW9mLXRlcnJvci1jaGFwdGVyLTEzOC8=",
      "date": "2 tahun yang lalu"
    },
    {
      "chapter": "137",
      "title": "Komik Age of Terror Chapter 137",
      "url": "b64:aHR0cHM6Ly9rb21pa2luZG8uY2gvYWdlLW9mLXRlcnJvci1jaGFwdGVyLTEzNy8=",
      "date": "2 tahun yang lalu"
    },
    {
      "chapter": "136",
      "title": "Komik Age of Terror Chapter 136",
      "url": "b64:aHR0cHM6Ly9rb21pa2luZG8uY2gvYWdlLW9mLXRlcnJvci1jaGFwdGVyLTEzNi8=",
      "date": "2 tahun yang lalu"
    },
    {
      "chapter": "135",
      "title": "Komik Age of Terror Chapter 135",
      "url": "b64:aHR0cHM6Ly9rb21pa2luZG8uY2gvYWdlLW9mLXRlcnJvci1jaGFwdGVyLTEzNS8=",
      "date": "2 tahun yang lalu"
    },
    {
      "chapter": "134",
      "title": "Komik Age of Terror Chapter 134",
      "url": "b64:aHR0cHM6Ly9rb21pa2luZG8uY2gvYWdlLW9mLXRlcnJvci1jaGFwdGVyLTEzNC8=",
      "date": "2 tahun yang lalu"
    },
    {
      "chapter": "133",
      "title": "Komik Age of Terror Chapter 133",
      "url": "b64:aHR0cHM6Ly9rb21pa2luZG8uY2gvYWdlLW9mLXRlcnJvci1jaGFwdGVyLTEzMy8=",
      "date": "2 tahun yang lalu"
    },
    {
      "chapter": "132",
      "title": "Komik Age of Terror Chapter 132",
      "url": "b64:aHR0cHM6Ly9rb21pa2luZG8uY2gvYWdlLW9mLXRlcnJvci1jaGFwdGVyLTEzMi8=",
      "date": "2 tahun yang lalu"
    },
    {
      "chapter": "131",
      "title": "Komik Age of Terror Chapter 131",
      "url": "b64:aHR0cHM6Ly9rb21pa2luZG8uY2gvYWdlLW9mLXRlcnJvci1jaGFwdGVyLTEzMS8=",
      "date": "2 tahun yang lalu"
    },
    {
      "chapter": "130",
      "title": "Komik Age of Terror Chapter 130",
      "url": "b64:aHR0cHM6Ly9rb21pa2luZG8uY2gvYWdlLW9mLXRlcnJvci1jaGFwdGVyLTEzMC8=",
      "date": "2 tahun yang lalu"
    },
    {
      "chapter": "129",
      "title": "Komik Age of Terror Chapter 129",
      "url": "b64:aHR0cHM6Ly9rb21pa2luZG8uY2gvYWdlLW9mLXRlcnJvci1jaGFwdGVyLTEyOS8=",
      "date": "2 tahun yang lalu"
    },
    {
      "chapter": "128",
      "title": "Komik Age of Terror Chapter 128",
      "url": "b64:aHR0cHM6Ly9rb21pa2luZG8uY2gvYWdlLW9mLXRlcnJvci1jaGFwdGVyLTEyOC8=",
      "date": "2 tahun yang lalu"
    },
    {
      "chapter": "127",
      "title": "Komik Age of Terror Chapter 127",
      "url": "b64:aHR0cHM6Ly9rb21pa2luZG8uY2gvYWdlLW9mLXRlcnJvci1jaGFwdGVyLTEyNy8=",
      "date": "2 tahun yang lalu"
    },
    {
      "chapter": "126",
      "title": "Komik Age of Terror Chapter 126",
      "url": "b64:aHR0cHM6Ly9rb21pa2luZG8uY2gvYWdlLW9mLXRlcnJvci1jaGFwdGVyLTEyNi8=",
      "date": "2 tahun yang lalu"
    },
    {
      "chapter": "125",
      "title": "Komik Age of Terror Chapter 125",
      "url": "b64:aHR0cHM6Ly9rb21pa2luZG8uY2gvYWdlLW9mLXRlcnJvci1jaGFwdGVyLTEyNS8=",
      "date": "2 tahun yang lalu"
    },
    {
      "chapter": "124",
      "title": "Komik Age of Terror Chapter 124",
      "url": "b64:aHR0cHM6Ly9rb21pa2luZG8uY2gvYWdlLW9mLXRlcnJvci1jaGFwdGVyLTEyNC8=",
      "date": "2 tahun yang lalu"
    },
    {
      "chapter": "123",
      "title": "Komik Age of Terror Chapter 123",
      "url": "b64:aHR0cHM6Ly9rb21pa2luZG8uY2gvYWdlLW9mLXRlcnJvci1jaGFwdGVyLTEyMy8=",
      "date": "2 tahun yang lalu"
    },
    {
      "chapter": "122",
      "title": "Komik Age of Terror Chapter 122",
      "url": "b64:aHR0cHM6Ly9rb21pa2luZG8uY2gvYWdlLW9mLXRlcnJvci1jaGFwdGVyLTEyMi8=",
      "date": "2 tahun yang lalu"
    },
    {
      "chapter": "121",
      "title": "Komik Age of Terror Chapter 121",
      "url": "b64:aHR0cHM6Ly9rb21pa2luZG8uY2gvYWdlLW9mLXRlcnJvci1jaGFwdGVyLTEyMS8=",
      "date": "2 tahun yang lalu"
    },
    {
      "chapter": "120",
      "title": "Komik Age of Terror Chapter 120",
      "url": "b64:aHR0cHM6Ly9rb21pa2luZG8uY2gvYWdlLW9mLXRlcnJvci1jaGFwdGVyLTEyMC8=",
      "date": "2 tahun yang lalu"
    },
    {
      "chapter": "119",
      "title": "Komik Age of Terror Chapter 119",
      "url": "b64:aHR0cHM6Ly9rb21pa2luZG8uY2gvYWdlLW9mLXRlcnJvci1jaGFwdGVyLTExOS8=",
      "date": "2 tahun yang lalu"
    },
    {
      "chapter": "118",
      "title": "Komik Age of Terror Chapter 118",
      "url": "b64:aHR0cHM6Ly9rb21pa2luZG8uY2gvYWdlLW9mLXRlcnJvci1jaGFwdGVyLTExOC8=",
      "date": "2 tahun yang lalu"
    },
    {
      "chapter": "117",
      "title": "Komik Age of Terror Chapter 117",
      "url": "b64:aHR0cHM6Ly9rb21pa2luZG8uY2gvYWdlLW9mLXRlcnJvci1jaGFwdGVyLTExNy8=",
      "date": "2 tahun yang lalu"
    },
    {
      "chapter": "116",
      "title": "Komik Age of Terror Chapter 116",
      "url": "b64:aHR0cHM6Ly9rb21pa2luZG8uY2gvYWdlLW9mLXRlcnJvci1jaGFwdGVyLTExNi8=",
      "date": "2 tahun yang lalu"
    },
    {
      "chapter": "115",
      "title": "Komik Age of Terror Chapter 115",
      "url": "b64:aHR0cHM6Ly9rb21pa2luZG8uY2gvYWdlLW9mLXRlcnJvci1jaGFwdGVyLTExNS8=",
      "date": "2 tahun yang lalu"
    },
    {
      "chapter": "114",
      "title": "Komik Age of Terror Chapter 114",
      "url": "b64:aHR0cHM6Ly9rb21pa2luZG8uY2gvYWdlLW9mLXRlcnJvci1jaGFwdGVyLTExNC8=",
      "date": "2 tahun yang lalu"
    },
    {
      "chapter": "113",
      "title": "Komik Age of Terror Chapter 113",
      "url": "b64:aHR0cHM6Ly9rb21pa2luZG8uY2gvYWdlLW9mLXRlcnJvci1jaGFwdGVyLTExMy8=",
      "date": "2 tahun yang lalu"
    },
    {
      "chapter": "112",
      "title": "Komik Age of Terror Chapter 112",
      "url": "b64:aHR0cHM6Ly9rb21pa2luZG8uY2gvYWdlLW9mLXRlcnJvci1jaGFwdGVyLTExMi8=",
      "date": "2 tahun yang lalu"
    },
    {
      "chapter": "111",
      "title": "Komik Age of Terror Chapter 111",
      "url": "b64:aHR0cHM6Ly9rb21pa2luZG8uY2gvYWdlLW9mLXRlcnJvci1jaGFwdGVyLTExMS8=",
      "date": "2 tahun yang lalu"
    },
    {
      "chapter": "110",
      "title": "Komik Age of Terror Chapter 110",
      "url": "b64:aHR0cHM6Ly9rb21pa2luZG8uY2gvYWdlLW9mLXRlcnJvci1jaGFwdGVyLTExMC8=",
      "date": "2 tahun yang lalu"
    },
    {
      "chapter": "109",
      "title": "Komik Age of Terror Chapter 109",
      "url": "b64:aHR0cHM6Ly9rb21pa2luZG8uY2gvYWdlLW9mLXRlcnJvci1jaGFwdGVyLTEwOS8=",
      "date": "2 tahun yang lalu"
    },
    {
      "chapter": "108",
      "title": "Komik Age of Terror Chapter 108",
      "url": "b64:aHR0cHM6Ly9rb21pa2luZG8uY2gvYWdlLW9mLXRlcnJvci1jaGFwdGVyLTEwOC8=",
      "date": "2 tahun yang lalu"
    },
    {
      "chapter": "107",
      "title": "Komik Age of Terror Chapter 107",
      "url": "b64:aHR0cHM6Ly9rb21pa2luZG8uY2gvYWdlLW9mLXRlcnJvci1jaGFwdGVyLTEwNy8=",
      "date": "2 tahun yang lalu"
    },
    {
      "chapter": "106",
      "title": "Komik Age of Terror Chapter 106",
      "url": "b64:aHR0cHM6Ly9rb21pa2luZG8uY2gvYWdlLW9mLXRlcnJvci1jaGFwdGVyLTEwNi8=",
      "date": "2 tahun yang lalu"
    },
    {
      "chapter": "105",
      "title": "Komik Age of Terror Chapter 105",
      "url": "b64:aHR0cHM6Ly9rb21pa2luZG8uY2gvYWdlLW9mLXRlcnJvci1jaGFwdGVyLTEwNS8=",
      "date": "2 tahun yang lalu"
    },
    {
      "chapter": "104",
      "title": "Komik Age of Terror Chapter 104",
      "url": "b64:aHR0cHM6Ly9rb21pa2luZG8uY2gvYWdlLW9mLXRlcnJvci1jaGFwdGVyLTEwNC8=",
      "date": "2 tahun yang lalu"
    },
    {
      "chapter": "103",
      "title": "Komik Age of Terror Chapter 103",
      "url": "b64:aHR0cHM6Ly9rb21pa2luZG8uY2gvYWdlLW9mLXRlcnJvci1jaGFwdGVyLTEwMy8=",
      "date": "2 tahun yang lalu"
    },
    {
      "chapter": "102",
      "title": "Komik Age of Terror Chapter 102",
      "url": "b64:aHR0cHM6Ly9rb21pa2luZG8uY2gvYWdlLW9mLXRlcnJvci1jaGFwdGVyLTEwMi8=",
      "date": "2 tahun yang lalu"
    },
    {
      "chapter": "101",
      "title": "Komik Age of Terror Chapter 101",
      "url": "b64:aHR0cHM6Ly9rb21pa2luZG8uY2gvYWdlLW9mLXRlcnJvci1jaGFwdGVyLTEwMS8=",
      "date": "2 tahun yang lalu"
    },
    {
      "chapter": "100",
      "title": "Komik Age of Terror Chapter 100",
      "url": "b64:aHR0cHM6Ly9rb21pa2luZG8uY2gvYWdlLW9mLXRlcnJvci1jaGFwdGVyLTEwMC8=",
      "date": "2 tahun yang lalu"
    },
    {
      "chapter": "99",
      "title": "Komik Age of Terror Chapter 99",
      "url": "b64:aHR0cHM6Ly9rb21pa2luZG8uY2gvYWdlLW9mLXRlcnJvci1jaGFwdGVyLTk5Lw==",
      "date": "2 tahun yang lalu"
    },
    {
      "chapter": "98",
      "title": "Komik Age of Terror Chapter 98",
      "url": "b64:aHR0cHM6Ly9rb21pa2luZG8uY2gvYWdlLW9mLXRlcnJvci1jaGFwdGVyLTk4Lw==",
      "date": "2 tahun yang lalu"
    },
    {
      "chapter": "97",
      "title": "Komik Age of Terror Chapter 97",
      "url": "b64:aHR0cHM6Ly9rb21pa2luZG8uY2gvYWdlLW9mLXRlcnJvci1jaGFwdGVyLTk3Lw==",
      "date": "3 tahun yang lalu"
    },
    {
      "chapter": "96",
      "title": "Komik Age of Terror Chapter 96",
      "url": "b64:aHR0cHM6Ly9rb21pa2luZG8uY2gvYWdlLW9mLXRlcnJvci1jaGFwdGVyLTk2Lw==",
      "date": "3 tahun yang lalu"
    },
    {
      "chapter": "95",
      "title": "Komik Age of Terror Chapter 95",
      "url": "b64:aHR0cHM6Ly9rb21pa2luZG8uY2gvYWdlLW9mLXRlcnJvci1jaGFwdGVyLTk1Lw==",
      "date": "3 tahun yang lalu"
    },
    {
      "chapter": "94",
      "title": "Komik Age of Terror Chapter 94",
      "url": "b64:aHR0cHM6Ly9rb21pa2luZG8uY2gvYWdlLW9mLXRlcnJvci1jaGFwdGVyLTk0Lw==",
      "date": "3 tahun yang lalu"
    },
    {
      "chapter": "93",
      "title": "Komik Age of Terror Chapter 93",
      "url": "b64:aHR0cHM6Ly9rb21pa2luZG8uY2gvYWdlLW9mLXRlcnJvci1jaGFwdGVyLTkzLw==",
      "date": "3 tahun yang lalu"
    },
    {
      "chapter": "92",
      "title": "Komik Age of Terror Chapter 92",
      "url": "b64:aHR0cHM6Ly9rb21pa2luZG8uY2gvYWdlLW9mLXRlcnJvci1jaGFwdGVyLTkyLw==",
      "date": "3 tahun yang lalu"
    },
    {
      "chapter": "91",
      "title": "Komik Age of Terror Chapter 91",
      "url": "b64:aHR0cHM6Ly9rb21pa2luZG8uY2gvYWdlLW9mLXRlcnJvci1jaGFwdGVyLTkxLw==",
      "date": "3 tahun yang lalu"
    },
    {
      "chapter": "90",
      "title": "Komik Age of Terror Chapter 90",
      "url": "b64:aHR0cHM6Ly9rb21pa2luZG8uY2gvYWdlLW9mLXRlcnJvci1jaGFwdGVyLTkwLw==",
      "date": "3 tahun yang lalu"
    },
    {
      "chapter": "89",
      "title": "Komik Age of Terror Chapter 89",
      "url": "b64:aHR0cHM6Ly9rb21pa2luZG8uY2gvYWdlLW9mLXRlcnJvci1jaGFwdGVyLTg5Lw==",
      "date": "3 tahun yang lalu"
    },
    {
      "chapter": "88",
      "title": "Komik Age of Terror Chapter 88",
      "url": "b64:aHR0cHM6Ly9rb21pa2luZG8uY2gvYWdlLW9mLXRlcnJvci1jaGFwdGVyLTg4Lw==",
      "date": "3 tahun yang lalu"
    },
    {
      "chapter": "87",
      "title": "Komik Age of Terror Chapter 87",
      "url": "b64:aHR0cHM6Ly9rb21pa2luZG8uY2gvYWdlLW9mLXRlcnJvci1jaGFwdGVyLTg3Lw==",
      "date": "3 tahun yang lalu"
    },
    {
      "chapter": "86",
      "title": "Komik Age of Terror Chapter 86",
      "url": "b64:aHR0cHM6Ly9rb21pa2luZG8uY2gvYWdlLW9mLXRlcnJvci1jaGFwdGVyLTg2Lw==",
      "date": "3 tahun yang lalu"
    },
    {
      "chapter": "85",
      "title": "Komik Age of Terror Chapter 85",
      "url": "b64:aHR0cHM6Ly9rb21pa2luZG8uY2gvYWdlLW9mLXRlcnJvci1jaGFwdGVyLTg1Lw==",
      "date": "3 tahun yang lalu"
    },
    {
      "chapter": "84",
      "title": "Komik Age of Terror Chapter 84",
      "url": "b64:aHR0cHM6Ly9rb21pa2luZG8uY2gvYWdlLW9mLXRlcnJvci1jaGFwdGVyLTg0Lw==",
      "date": "3 tahun yang lalu"
    },
    {
      "chapter": "83",
      "title": "Komik Age of Terror Chapter 83",
      "url": "b64:aHR0cHM6Ly9rb21pa2luZG8uY2gvYWdlLW9mLXRlcnJvci1jaGFwdGVyLTgzLw==",
      "date": "3 tahun yang lalu"
    },
    {
      "chapter": "82",
      "title": "Komik Age of Terror Chapter 82",
      "url": "b64:aHR0cHM6Ly9rb21pa2luZG8uY2gvYWdlLW9mLXRlcnJvci1jaGFwdGVyLTgyLw==",
      "date": "3 tahun yang lalu"
    },
    {
      "chapter": "81",
      "title": "Komik Age of Terror Chapter 81",
      "url": "b64:aHR0cHM6Ly9rb21pa2luZG8uY2gvYWdlLW9mLXRlcnJvci1jaGFwdGVyLTgxLw==",
      "date": "3 tahun yang lalu"
    },
    {
      "chapter": "80",
      "title": "Komik Age of Terror Chapter 80",
      "url": "b64:aHR0cHM6Ly9rb21pa2luZG8uY2gvYWdlLW9mLXRlcnJvci1jaGFwdGVyLTgwLw==",
      "date": "3 tahun yang lalu"
    },
    {
      "chapter": "79",
      "title": "Komik Age of Terror Chapter 79",
      "url": "b64:aHR0cHM6Ly9rb21pa2luZG8uY2gvYWdlLW9mLXRlcnJvci1jaGFwdGVyLTc5Lw==",
      "date": "3 tahun yang lalu"
    },
    {
      "chapter": "78",
      "title": "Komik Age of Terror Chapter 78",
      "url": "b64:aHR0cHM6Ly9rb21pa2luZG8uY2gvYWdlLW9mLXRlcnJvci1jaGFwdGVyLTc4Lw==",
      "date": "3 tahun yang lalu"
    },
    {
      "chapter": "77",
      "title": "Komik Age of Terror Chapter 77",
      "url": "b64:aHR0cHM6Ly9rb21pa2luZG8uY2gvYWdlLW9mLXRlcnJvci1jaGFwdGVyLTc3Lw==",
      "date": "3 tahun yang lalu"
    },
    {
      "chapter": "76",
      "title": "Komik Age of Terror Chapter 76",
      "url": "b64:aHR0cHM6Ly9rb21pa2luZG8uY2gvYWdlLW9mLXRlcnJvci1jaGFwdGVyLTc2Lw==",
      "date": "3 tahun yang lalu"
    },
    {
      "chapter": "75",
      "title": "Komik Age of Terror Chapter 75",
      "url": "b64:aHR0cHM6Ly9rb21pa2luZG8uY2gvYWdlLW9mLXRlcnJvci1jaGFwdGVyLTc1Lw==",
      "date": "3 tahun yang lalu"
    },
    {
      "chapter": "74",
      "title": "Komik Age of Terror Chapter 74",
      "url": "b64:aHR0cHM6Ly9rb21pa2luZG8uY2gvYWdlLW9mLXRlcnJvci1jaGFwdGVyLTc0Lw==",
      "date": "3 tahun yang lalu"
    },
    {
      "chapter": "73",
      "title": "Komik Age of Terror Chapter 73",
      "url": "b64:aHR0cHM6Ly9rb21pa2luZG8uY2gvYWdlLW9mLXRlcnJvci1jaGFwdGVyLTczLw==",
      "date": "3 tahun yang lalu"
    },
    {
      "chapter": "72",
      "title": "Komik Age of Terror Chapter 72",
      "url": "b64:aHR0cHM6Ly9rb21pa2luZG8uY2gvYWdlLW9mLXRlcnJvci1jaGFwdGVyLTcyLw==",
      "date": "3 tahun yang lalu"
    },
    {
      "chapter": "71",
      "title": "Komik Age of Terror Chapter 71",
      "url": "b64:aHR0cHM6Ly9rb21pa2luZG8uY2gvYWdlLW9mLXRlcnJvci1jaGFwdGVyLTcxLw==",
      "date": "3 tahun yang lalu"
    },
    {
      "chapter": "70",
      "title": "Komik Age of Terror Chapter 70",
      "url": "b64:aHR0cHM6Ly9rb21pa2luZG8uY2gvYWdlLW9mLXRlcnJvci1jaGFwdGVyLTcwLw==",
      "date": "3 tahun yang lalu"
    },
    {
      "chapter": "69",
      "title": "Komik Age of Terror Chapter 69",
      "url": "b64:aHR0cHM6Ly9rb21pa2luZG8uY2gvYWdlLW9mLXRlcnJvci1jaGFwdGVyLTY5Lw==",
      "date": "3 tahun yang lalu"
    },
    {
      "chapter": "68",
      "title": "Komik Age of Terror Chapter 68",
      "url": "b64:aHR0cHM6Ly9rb21pa2luZG8uY2gvYWdlLW9mLXRlcnJvci1jaGFwdGVyLTY4Lw==",
      "date": "3 tahun yang lalu"
    },
    {
      "chapter": "67",
      "title": "Komik Age of Terror Chapter 67",
      "url": "b64:aHR0cHM6Ly9rb21pa2luZG8uY2gvYWdlLW9mLXRlcnJvci1jaGFwdGVyLTY3Lw==",
      "date": "3 tahun yang lalu"
    },
    {
      "chapter": "66",
      "title": "Komik Age of Terror Chapter 66",
      "url": "b64:aHR0cHM6Ly9rb21pa2luZG8uY2gvYWdlLW9mLXRlcnJvci1jaGFwdGVyLTY2Lw==",
      "date": "3 tahun yang lalu"
    },
    {
      "chapter": "65",
      "title": "Komik Age of Terror Chapter 65",
      "url": "b64:aHR0cHM6Ly9rb21pa2luZG8uY2gvYWdlLW9mLXRlcnJvci1jaGFwdGVyLTY1Lw==",
      "date": "3 tahun yang lalu"
    },
    {
      "chapter": "64",
      "title": "Komik Age of Terror Chapter 64",
      "url": "b64:aHR0cHM6Ly9rb21pa2luZG8uY2gvYWdlLW9mLXRlcnJvci1jaGFwdGVyLTY0Lw==",
      "date": "3 tahun yang lalu"
    },
    {
      "chapter": "63",
      "title": "Komik Age of Terror Chapter 63",
      "url": "b64:aHR0cHM6Ly9rb21pa2luZG8uY2gvYWdlLW9mLXRlcnJvci1jaGFwdGVyLTYzLw==",
      "date": "3 tahun yang lalu"
    },
    {
      "chapter": "62",
      "title": "Komik Age of Terror Chapter 62",
      "url": "b64:aHR0cHM6Ly9rb21pa2luZG8uY2gvYWdlLW9mLXRlcnJvci1jaGFwdGVyLTYyLw==",
      "date": "3 tahun yang lalu"
    },
    {
      "chapter": "61",
      "title": "Komik Age of Terror Chapter 61",
      "url": "b64:aHR0cHM6Ly9rb21pa2luZG8uY2gvYWdlLW9mLXRlcnJvci1jaGFwdGVyLTYxLw==",
      "date": "3 tahun yang lalu"
    },
    {
      "chapter": "60",
      "title": "Komik Age of Terror Chapter 60",
      "url": "b64:aHR0cHM6Ly9rb21pa2luZG8uY2gvYWdlLW9mLXRlcnJvci1jaGFwdGVyLTYwLw==",
      "date": "3 tahun yang lalu"
    },
    {
      "chapter": "59",
      "title": "Komik Age of Terror Chapter 59",
      "url": "b64:aHR0cHM6Ly9rb21pa2luZG8uY2gvYWdlLW9mLXRlcnJvci1jaGFwdGVyLTU5Lw==",
      "date": "3 tahun yang lalu"
    },
    {
      "chapter": "58",
      "title": "Komik Age of Terror Chapter 58",
      "url": "b64:aHR0cHM6Ly9rb21pa2luZG8uY2gvYWdlLW9mLXRlcnJvci1jaGFwdGVyLTU4Lw==",
      "date": "3 tahun yang lalu"
    },
    {
      "chapter": "57",
      "title": "Komik Age of Terror Chapter 57",
      "url": "b64:aHR0cHM6Ly9rb21pa2luZG8uY2gvYWdlLW9mLXRlcnJvci1jaGFwdGVyLTU3Lw==",
      "date": "3 tahun yang lalu"
    },
    {
      "chapter": "56",
      "title": "Komik Age of Terror Chapter 56",
      "url": "b64:aHR0cHM6Ly9rb21pa2luZG8uY2gvYWdlLW9mLXRlcnJvci1jaGFwdGVyLTU2Lw==",
      "date": "3 tahun yang lalu"
    },
    {
      "chapter": "55",
      "title": "Komik Age of Terror Chapter 55",
      "url": "b64:aHR0cHM6Ly9rb21pa2luZG8uY2gvYWdlLW9mLXRlcnJvci1jaGFwdGVyLTU1Lw==",
      "date": "3 tahun yang lalu"
    },
    {
      "chapter": "54",
      "title": "Komik Age of Terror Chapter 54",
      "url": "b64:aHR0cHM6Ly9rb21pa2luZG8uY2gvYWdlLW9mLXRlcnJvci1jaGFwdGVyLTU0Lw==",
      "date": "3 tahun yang lalu"
    },
    {
      "chapter": "53",
      "title": "Komik Age of Terror Chapter 53",
      "url": "b64:aHR0cHM6Ly9rb21pa2luZG8uY2gvYWdlLW9mLXRlcnJvci1jaGFwdGVyLTUzLw==",
      "date": "3 tahun yang lalu"
    },
    {
      "chapter": "52",
      "title": "Komik Age of Terror Chapter 52",
      "url": "b64:aHR0cHM6Ly9rb21pa2luZG8uY2gvYWdlLW9mLXRlcnJvci1jaGFwdGVyLTUyLw==",
      "date": "3 tahun yang lalu"
    },
    {
      "chapter": "51",
      "title": "Komik Age of Terror Chapter 51",
      "url": "b64:aHR0cHM6Ly9rb21pa2luZG8uY2gvYWdlLW9mLXRlcnJvci1jaGFwdGVyLTUxLw==",
      "date": "3 tahun yang lalu"
    },
    {
      "chapter": "50",
      "title": "Komik Age of Terror Chapter 50",
      "url": "b64:aHR0cHM6Ly9rb21pa2luZG8uY2gvYWdlLW9mLXRlcnJvci1jaGFwdGVyLTUwLw==",
      "date": "3 tahun yang lalu"
    },
    {
      "chapter": "49",
      "title": "Komik Age of Terror Chapter 49",
      "url": "b64:aHR0cHM6Ly9rb21pa2luZG8uY2gvYWdlLW9mLXRlcnJvci1jaGFwdGVyLTQ5Lw==",
      "date": "3 tahun yang lalu"
    },
    {
      "chapter": "48",
      "title": "Komik Age of Terror Chapter 48",
      "url": "b64:aHR0cHM6Ly9rb21pa2luZG8uY2gvYWdlLW9mLXRlcnJvci1jaGFwdGVyLTQ4Lw==",
      "date": "3 tahun yang lalu"
    },
    {
      "chapter": "47",
      "title": "Komik Age of Terror Chapter 47",
      "url": "b64:aHR0cHM6Ly9rb21pa2luZG8uY2gvYWdlLW9mLXRlcnJvci1jaGFwdGVyLTQ3Lw==",
      "date": "3 tahun yang lalu"
    },
    {
      "chapter": "46",
      "title": "Komik Age of Terror Chapter 46",
      "url": "b64:aHR0cHM6Ly9rb21pa2luZG8uY2gvYWdlLW9mLXRlcnJvci1jaGFwdGVyLTQ2Lw==",
      "date": "3 tahun yang lalu"
    },
    {
      "chapter": "45",
      "title": "Komik Age of Terror Chapter 45",
      "url": "b64:aHR0cHM6Ly9rb21pa2luZG8uY2gvYWdlLW9mLXRlcnJvci1jaGFwdGVyLTQ1Lw==",
      "date": "3 tahun yang lalu"
    },
    {
      "chapter": "44",
      "title": "Komik Age of Terror Chapter 44",
      "url": "b64:aHR0cHM6Ly9rb21pa2luZG8uY2gvYWdlLW9mLXRlcnJvci1jaGFwdGVyLTQ0Lw==",
      "date": "3 tahun yang lalu"
    },
    {
      "chapter": "43",
      "title": "Komik Age of Terror Chapter 43",
      "url": "b64:aHR0cHM6Ly9rb21pa2luZG8uY2gvYWdlLW9mLXRlcnJvci1jaGFwdGVyLTQzLw==",
      "date": "3 tahun yang lalu"
    },
    {
      "chapter": "42",
      "title": "Komik Age of Terror Chapter 42",
      "url": "b64:aHR0cHM6Ly9rb21pa2luZG8uY2gvYWdlLW9mLXRlcnJvci1jaGFwdGVyLTQyLw==",
      "date": "3 tahun yang lalu"
    },
    {
      "chapter": "41",
      "title": "Komik Age of Terror Chapter 41",
      "url": "b64:aHR0cHM6Ly9rb21pa2luZG8uY2gvYWdlLW9mLXRlcnJvci1jaGFwdGVyLTQxLw==",
      "date": "3 tahun yang lalu"
    },
    {
      "chapter": "40",
      "title": "Komik Age of Terror Chapter 40",
      "url": "b64:aHR0cHM6Ly9rb21pa2luZG8uY2gvYWdlLW9mLXRlcnJvci1jaGFwdGVyLTQwLw==",
      "date": "3 tahun yang lalu"
    },
    {
      "chapter": "39",
      "title": "Komik Age of Terror Chapter 39",
      "url": "b64:aHR0cHM6Ly9rb21pa2luZG8uY2gvYWdlLW9mLXRlcnJvci1jaGFwdGVyLTM5Lw==",
      "date": "3 tahun yang lalu"
    },
    {
      "chapter": "38",
      "title": "Komik Age of Terror Chapter 38",
      "url": "b64:aHR0cHM6Ly9rb21pa2luZG8uY2gvYWdlLW9mLXRlcnJvci1jaGFwdGVyLTM4Lw==",
      "date": "3 tahun yang lalu"
    },
    {
      "chapter": "37",
      "title": "Komik Age of Terror Chapter 37",
      "url": "b64:aHR0cHM6Ly9rb21pa2luZG8uY2gvYWdlLW9mLXRlcnJvci1jaGFwdGVyLTM3Lw==",
      "date": "3 tahun yang lalu"
    },
    {
      "chapter": "36",
      "title": "Komik Age of Terror Chapter 36",
      "url": "b64:aHR0cHM6Ly9rb21pa2luZG8uY2gvYWdlLW9mLXRlcnJvci1jaGFwdGVyLTM2Lw==",
      "date": "3 tahun yang lalu"
    },
    {
      "chapter": "35",
      "title": "Komik Age of Terror Chapter 35",
      "url": "b64:aHR0cHM6Ly9rb21pa2luZG8uY2gvYWdlLW9mLXRlcnJvci1jaGFwdGVyLTM1Lw==",
      "date": "3 tahun yang lalu"
    },
    {
      "chapter": "34",
      "title": "Komik Age of Terror Chapter 34",
      "url": "b64:aHR0cHM6Ly9rb21pa2luZG8uY2gvYWdlLW9mLXRlcnJvci1jaGFwdGVyLTM0Lw==",
      "date": "3 tahun yang lalu"
    },
    {
      "chapter": "33",
      "title": "Komik Age of Terror Chapter 33",
      "url": "b64:aHR0cHM6Ly9rb21pa2luZG8uY2gvYWdlLW9mLXRlcnJvci1jaGFwdGVyLTMzLw==",
      "date": "3 tahun yang lalu"
    },
    {
      "chapter": "32",
      "title": "Komik Age of Terror Chapter 32",
      "url": "b64:aHR0cHM6Ly9rb21pa2luZG8uY2gvYWdlLW9mLXRlcnJvci1jaGFwdGVyLTMyLw==",
      "date": "3 tahun yang lalu"
    },
    {
      "chapter": "31",
      "title": "Komik Age of Terror Chapter 31",
      "url": "b64:aHR0cHM6Ly9rb21pa2luZG8uY2gvYWdlLW9mLXRlcnJvci1jaGFwdGVyLTMxLw==",
      "date": "3 tahun yang lalu"
    },
    {
      "chapter": "30",
      "title": "Komik Age of Terror Chapter 30",
      "url": "b64:aHR0cHM6Ly9rb21pa2luZG8uY2gvYWdlLW9mLXRlcnJvci1jaGFwdGVyLTMwLw==",
      "date": "3 tahun yang lalu"
    },
    {
      "chapter": "29",
      "title": "Komik Age of Terror Chapter 29",
      "url": "b64:aHR0cHM6Ly9rb21pa2luZG8uY2gvYWdlLW9mLXRlcnJvci1jaGFwdGVyLTI5Lw==",
      "date": "3 tahun yang lalu"
    },
    {
      "chapter": "28",
      "title": "Komik Age of Terror Chapter 28",
      "url": "b64:aHR0cHM6Ly9rb21pa2luZG8uY2gvYWdlLW9mLXRlcnJvci1jaGFwdGVyLTI4Lw==",
      "date": "3 tahun yang lalu"
    },
    {
      "chapter": "27",
      "title": "Komik Age of Terror Chapter 27",
      "url": "b64:aHR0cHM6Ly9rb21pa2luZG8uY2gvYWdlLW9mLXRlcnJvci1jaGFwdGVyLTI3Lw==",
      "date": "3 tahun yang lalu"
    },
    {
      "chapter": "26.5",
      "title": "Komik Age of Terror Chapter 26.5",
      "url": "b64:aHR0cHM6Ly9rb21pa2luZG8uY2gvYWdlLW9mLXRlcnJvci1jaGFwdGVyLTI2LTUv",
      "date": "3 tahun yang lalu"
    },
    {
      "chapter": "26",
      "title": "Komik Age of Terror Chapter 26",
      "url": "b64:aHR0cHM6Ly9rb21pa2luZG8uY2gvYWdlLW9mLXRlcnJvci1jaGFwdGVyLTI2Lw==",
      "date": "3 tahun yang lalu"
    },
    {
      "chapter": "25.5",
      "title": "Komik Age of Terror Chapter 25.5",
      "url": "b64:aHR0cHM6Ly9rb21pa2luZG8uY2gvYWdlLW9mLXRlcnJvci1jaGFwdGVyLTI1LTUv",
      "date": "3 tahun yang lalu"
    },
    {
      "chapter": "25",
      "title": "Komik Age of Terror Chapter 25",
      "url": "b64:aHR0cHM6Ly9rb21pa2luZG8uY2gvYWdlLW9mLXRlcnJvci1jaGFwdGVyLTI1Lw==",
      "date": "3 tahun yang lalu"
    },
    {
      "chapter": "24",
      "title": "Komik Age of Terror Chapter 24",
      "url": "b64:aHR0cHM6Ly9rb21pa2luZG8uY2gvYWdlLW9mLXRlcnJvci1jaGFwdGVyLTI0Lw==",
      "date": "3 tahun yang lalu"
    },
    {
      "chapter": "23",
      "title": "Komik Age of Terror Chapter 23",
      "url": "b64:aHR0cHM6Ly9rb21pa2luZG8uY2gvYWdlLW9mLXRlcnJvci1jaGFwdGVyLTIzLw==",
      "date": "3 tahun yang lalu"
    },
    {
      "chapter": "22",
      "title": "Komik Age of Terror Chapter 22",
      "url": "b64:aHR0cHM6Ly9rb21pa2luZG8uY2gvYWdlLW9mLXRlcnJvci1jaGFwdGVyLTIyLw==",
      "date": "3 tahun yang lalu"
    },
    {
      "chapter": "21",
      "title": "Komik Age of Terror Chapter 21",
      "url": "b64:aHR0cHM6Ly9rb21pa2luZG8uY2gvYWdlLW9mLXRlcnJvci1jaGFwdGVyLTIxLw==",
      "date": "3 tahun yang lalu"
    },
    {
      "chapter": "20",
      "title": "Komik Age of Terror Chapter 20",
      "url": "b64:aHR0cHM6Ly9rb21pa2luZG8uY2gvYWdlLW9mLXRlcnJvci1jaGFwdGVyLTIwLw==",
      "date": "3 tahun yang lalu"
    },
    {
      "chapter": "19",
      "title": "Komik Age of Terror Chapter 19",
      "url": "b64:aHR0cHM6Ly9rb21pa2luZG8uY2gvYWdlLW9mLXRlcnJvci1jaGFwdGVyLTE5Lw==",
      "date": "3 tahun yang lalu"
    },
    {
      "chapter": "18",
      "title": "Komik Age of Terror Chapter 18",
      "url": "b64:aHR0cHM6Ly9rb21pa2luZG8uY2gvYWdlLW9mLXRlcnJvci1jaGFwdGVyLTE4Lw==",
      "date": "3 tahun yang lalu"
    },
    {
      "chapter": "17",
      "title": "Komik Age of Terror Chapter 17",
      "url": "b64:aHR0cHM6Ly9rb21pa2luZG8uY2gvYWdlLW9mLXRlcnJvci1jaGFwdGVyLTE3Lw==",
      "date": "4 tahun yang lalu"
    },
    {
      "chapter": "16",
      "title": "Komik Age of Terror Chapter 16",
      "url": "b64:aHR0cHM6Ly9rb21pa2luZG8uY2gvYWdlLW9mLXRlcnJvci1jaGFwdGVyLTE2Lw==",
      "date": "4 tahun yang lalu"
    },
    {
      "chapter": "15",
      "title": "Komik Age of Terror Chapter 15",
      "url": "b64:aHR0cHM6Ly9rb21pa2luZG8uY2gvYWdlLW9mLXRlcnJvci1jaGFwdGVyLTE1Lw==",
      "date": "4 tahun yang lalu"
    },
    {
      "chapter": "14",
      "title": "Komik Age of Terror Chapter 14",
      "url": "b64:aHR0cHM6Ly9rb21pa2luZG8uY2gvYWdlLW9mLXRlcnJvci1jaGFwdGVyLTE0Lw==",
      "date": "4 tahun yang lalu"
    },
    {
      "chapter": "13",
      "title": "Komik Age of Terror Chapter 13",
      "url": "b64:aHR0cHM6Ly9rb21pa2luZG8uY2gvYWdlLW9mLXRlcnJvci1jaGFwdGVyLTEzLw==",
      "date": "4 tahun yang lalu"
    },
    {
      "chapter": "12",
      "title": "Komik Age of Terror Chapter 12",
      "url": "b64:aHR0cHM6Ly9rb21pa2luZG8uY2gvYWdlLW9mLXRlcnJvci1jaGFwdGVyLTEyLw==",
      "date": "4 tahun yang lalu"
    },
    {
      "chapter": "11",
      "title": "Komik Age of Terror Chapter 11",
      "url": "b64:aHR0cHM6Ly9rb21pa2luZG8uY2gvYWdlLW9mLXRlcnJvci1jaGFwdGVyLTExLw==",
      "date": "4 tahun yang lalu"
    },
    {
      "chapter": "10",
      "title": "Komik Age of Terror Chapter 10",
      "url": "b64:aHR0cHM6Ly9rb21pa2luZG8uY2gvYWdlLW9mLXRlcnJvci1jaGFwdGVyLTEwLw==",
      "date": "4 tahun yang lalu"
    },
    {
      "chapter": "9",
      "title": "Komik Age of Terror Chapter 9",
      "url": "b64:aHR0cHM6Ly9rb21pa2luZG8uY2gvYWdlLW9mLXRlcnJvci1jaGFwdGVyLTkv",
      "date": "4 tahun yang lalu"
    },
    {
      "chapter": "8",
      "title": "Komik Age of Terror Chapter 8",
      "url": "b64:aHR0cHM6Ly9rb21pa2luZG8uY2gvYWdlLW9mLXRlcnJvci1jaGFwdGVyLTgv",
      "date": "4 tahun yang lalu"
    },
    {
      "chapter": "7",
      "title": "Komik Age of Terror Chapter 7",
      "url": "b64:aHR0cHM6Ly9rb21pa2luZG8uY2gvYWdlLW9mLXRlcnJvci1jaGFwdGVyLTcv",
      "date": "4 tahun yang lalu"
    },
    {
      "chapter": "6",
      "title": "Komik Age of Terror Chapter 6",
      "url": "b64:aHR0cHM6Ly9rb21pa2luZG8uY2gvYWdlLW9mLXRlcnJvci1jaGFwdGVyLTYv",
      "date": "4 tahun yang lalu"
    },
    {
      "chapter": "5",
      "title": "Komik Age of Terror Chapter 5",
      "url": "b64:aHR0cHM6Ly9rb21pa2luZG8uY2gvYWdlLW9mLXRlcnJvci1jaGFwdGVyLTUv",
      "date": "4 tahun yang lalu"
    },
    {
      "chapter": "4",
      "title": "Komik Age of Terror Chapter 4",
      "url": "b64:aHR0cHM6Ly9rb21pa2luZG8uY2gvYWdlLW9mLXRlcnJvci1jaGFwdGVyLTQv",
      "date": "4 tahun yang lalu"
    },
    {
      "chapter": "3",
      "title": "Komik Age of Terror Chapter 3",
      "url": "b64:aHR0cHM6Ly9rb21pa2luZG8uY2gvYWdlLW9mLXRlcnJvci1jaGFwdGVyLTMv",
      "date": "4 tahun yang lalu"
    },
    {
      "chapter": "2",
      "title": "Komik Age of Terror Chapter 2",
      "url": "b64:aHR0cHM6Ly9rb21pa2luZG8uY2gvYWdlLW9mLXRlcnJvci1jaGFwdGVyLTIv",
      "date": "4 tahun yang lalu"
    },
    {
      "chapter": "1",
      "title": "Komik Age of Terror Chapter 1",
      "url": "b64:aHR0cHM6Ly9rb21pa2luZG8uY2gvYWdlLW9mLXRlcnJvci1jaGFwdGVyLTEv",
      "date": "4 tahun yang lalu"
    }
  ],
  "total_chapters": 304
}